notion_calendar_generator/__init__.py
notion_calendar_generator/calendar_generator.py
notion_calendar_generator/main.py
notion_calendar_generator/notion.py
notion_calendar_generator/utils.py
notion_calendar_generator-0.0.4.dist-info/entry_points.txt
notion_calendar_generator-0.0.4.dist-info/METADATA
notion_calendar_generator-0.0.4.dist-info/WHEEL
notion_calendar_generator-0.0.4.dist-info/RECORD
